

{ 
    "Characters": {
        "Traveller": {
        	"Default": "Sprites/Test/Default.png"
        },
        "Heizou": {
        	"Default": "Sprite/Test/Default.png"
        },

		"Null":{

		}
		
    },
    
    "Scene1": {
    	"Background": "Backgrounds/Dock_Crime.png",
    	"PAGES": {
			"Page0" : {
				"Character": "Traveller",
				"Sprite": "Default",
				"PageText": "Just pretend there is something meaningful here"
				
			},
			"Page1" : {
				"Character": "Traveller",
				"Sprite": "Default",
				"PageText": "Page 1 "
				
			},

			"Page3" : {
				"Character": "Null",
				"Sprite": "Restr",
				"PageText": " ",
				"Options":
				{
					"Finish?": "Page10",
					"Restart?": "Page0"
				}
				
			},
			"Page10" : {
				"Character": "Me",
				"Sprite": "Thinking",
				"PageText": "Thank you for reading!",
				"NextPage": "End"
				
			}
		}

    },

	"Scene2": {
    	"Background": "Backgrounds/Dock_Crime.png",
    	"PAGES": {
			"Page0" : {
				"Character": "Traveller",
				"Sprite": "Default",
				"PageText": "Just pretend there is something meaningful here"
				
			},
			"Page1" : {
				"Character": "Traveller",
				"Sprite": "Default",
				"PageText": "Page 1 "
				
			},

			"Page3" : {
				"Character": "Null",
				"Sprite": "Restr",
				"PageText": " ",
				"Options":
				{
					"Investigate?": "Investigate",
					"Restart?": "Page0"
				}
				
			},
			"Page10" : {
				"Character": "Me",
				"Sprite": "Thinking",
				"PageText": "Thank you for reading!",
				"NextPage": "End"
				
			}
		}
		
    }
}


